bitbucket_hg_exporter/__init__.py
bitbucket_hg_exporter/__main__.py
bitbucket_hg_exporter/__version__.py
bitbucket_hg_exporter/hg2git.py
bitbucket_hg_exporter/issue_migrate.py
bitbucket_hg_exporter/gh-pages-template/index.html
bitbucket_hg_exporter/gh-pages-template/ng/app.config.js
bitbucket_hg_exporter/gh-pages-template/ng/app.module.js
bitbucket_hg_exporter/gh-pages-template/ng/icon-approved.svg
bitbucket_hg_exporter/gh-pages-template/ng/commit-details/commit-details.component.js
bitbucket_hg_exporter/gh-pages-template/ng/commit-details/commit-details.module.js
bitbucket_hg_exporter/gh-pages-template/ng/commit-details/commit-details.template.html
bitbucket_hg_exporter/gh-pages-template/ng/commits-list/commits-list.component.js
bitbucket_hg_exporter/gh-pages-template/ng/commits-list/commits-list.module.js
bitbucket_hg_exporter/gh-pages-template/ng/commits-list/commits-list.template.html
bitbucket_hg_exporter/gh-pages-template/ng/index-page/author.template.html
bitbucket_hg_exporter/gh-pages-template/ng/index-page/index-page.component.js
bitbucket_hg_exporter/gh-pages-template/ng/index-page/index-page.module.js
bitbucket_hg_exporter/gh-pages-template/ng/index-page/index-page.template.html
bitbucket_hg_exporter/gh-pages-template/ng/issue-details/issue-details.component.js
bitbucket_hg_exporter/gh-pages-template/ng/issue-details/issue-details.module.js
bitbucket_hg_exporter/gh-pages-template/ng/issue-details/issue-details.template.html
bitbucket_hg_exporter/gh-pages-template/ng/issues-list/issues-list.component.js
bitbucket_hg_exporter/gh-pages-template/ng/issues-list/issues-list.module.js
bitbucket_hg_exporter/gh-pages-template/ng/issues-list/issues-list.template.html
bitbucket_hg_exporter/gh-pages-template/ng/pullrequest-details/pullrequest-details.component.js
bitbucket_hg_exporter/gh-pages-template/ng/pullrequest-details/pullrequest-details.module.js
bitbucket_hg_exporter/gh-pages-template/ng/pullrequest-details/pullrequest-details.template.html
bitbucket_hg_exporter-0.8.1.dist-info/LICENSE
bitbucket_hg_exporter-0.8.1.dist-info/METADATA
bitbucket_hg_exporter-0.8.1.dist-info/WHEEL
bitbucket_hg_exporter-0.8.1.dist-info/entry_points.txt
bitbucket_hg_exporter-0.8.1.dist-info/top_level.txt
bitbucket_hg_exporter-0.8.1.dist-info/RECORD
