Metadata-Version: 2.1
Name: bitbucket-hg-exporter
Version: 0.8.1
Summary: A tool for exporting all project data from a BitBucket mercurial repository
Home-page: https://github.com/philipstarkey/bitbucket-hg-exporter
Author: Philip Starkey
License: UNKNOWN
Project-URL: Source Code, https://github.com/philipstarkey/bitbucket-hg-exporter
Platform: UNKNOWN
Classifier: Development Status :: 3 - Alpha
Classifier: Programming Language :: Python :: 3.7
Classifier: Environment :: Console
Classifier: Intended Audience :: Developers
Classifier: License :: OSI Approved :: GNU General Public License v3 (GPLv3)
Classifier: Natural Language :: English
Classifier: Operating System :: OS Independent
Requires-Python: >=3.7, <4
Requires-Dist: keyring
Requires-Dist: requests
Requires-Dist: questionary
Requires-Dist: python-dateutil
Requires-Dist: colorama
Requires-Dist: cffi
